oms.py
oms-0.5.0.dist-info/LICENSE
oms-0.5.0.dist-info/METADATA
oms-0.5.0.dist-info/WHEEL
oms-0.5.0.dist-info/entry_points.txt
oms-0.5.0.dist-info/top_level.txt
oms-0.5.0.dist-info/RECORD
