Metadata-Version: 2.1
Name: oms
Version: 0.5.0
Summary: A micro-framework for the OMS, and code written in Python 3.6+.
Home-page: https://github.com/microservices/oms.py
Author: Storyscript
Author-email: support@storyscript.io
License: MIT
Platform: UNKNOWN
Classifier: License :: OSI Approved :: MIT License
Classifier: Programming Language :: Python
Classifier: Programming Language :: Python :: 3
Classifier: Programming Language :: Python :: 3.6
Classifier: Programming Language :: Python :: 3.7
Classifier: Programming Language :: Python :: Implementation :: CPython
Classifier: Programming Language :: Python :: Implementation :: PyPy
Requires-Python: >=3.6.0
Requires-Dist: pyyaml
Requires-Dist: Flask
Requires-Dist: waitress
Requires-Dist: setproctitle
Requires-Dist: docopt
Requires-Dist: inflection
